plockchain/__init__.py
plockchain/chain.py
plockchain/request.py
plockchain/utils.py
plockchain-2025.5.19.dist-info/METADATA
plockchain-2025.5.19.dist-info/WHEEL
plockchain-2025.5.19.dist-info/top_level.txt
plockchain-2025.5.19.dist-info/RECORD
