Metadata-Version: 2.4
Name: plockchain
Version: 2025.5.19
Summary: plockchain support for send request flow by write yaml config file
Home-page: https://github.com/nquangit/plockchain
Author: nquangit
Author-email: nquang.it.04@gmail.com
License: MIT
Keywords: nquangit,plockchain
Classifier: Programming Language :: Python :: 3
Requires-Dist: jq==1.8.0
Requires-Dist: pystache==0.6.8
Requires-Dist: PyYAML==6.0.2
Dynamic: author
Dynamic: author-email
Dynamic: classifier
Dynamic: description
Dynamic: description-content-type
Dynamic: home-page
Dynamic: keywords
Dynamic: license
Dynamic: requires-dist
Dynamic: summary
